auto_check/__init__.py
auto_check/__main__.py
auto_check/bean/__init__.py
auto_check/bean/property.py
auto_check/checker/__init__.py
auto_check/checker/auto_checker.py
auto_check/common/__init__.py
auto_check/common/parse_params.py
auto_check-0.0.dist-info/METADATA
auto_check-0.0.dist-info/WHEEL
auto_check-0.0.dist-info/entry_points.txt
auto_check-0.0.dist-info/top_level.txt
auto_check-0.0.dist-info/RECORD
