Metadata-Version: 2.1
Name: auto-check
Version: 0.0
Summary: 主要用于针对使用E-Mobile自动打卡
Home-page: https://github.com/sasuraiu/autocheck
Author: 一条肥鱼
Author-email: sasuraiu@gmail.com
Maintainer: 一条肥鱼
Maintainer-email: sasuraiu@gmail.com
License: MIT License
Platform: all
Requires-Dist: requests
